mio_decomp/__init__.py
mio_decomp/__main__.py
mio_decomp/main.py
mio_decomp/src/__init__.py
mio_decomp/src/app.py
mio_decomp/src/commands/__init__.py
mio_decomp/src/commands/check.py
mio_decomp/src/commands/config/__init__.py
mio_decomp/src/commands/config/get.py
mio_decomp/src/commands/config/list.py
mio_decomp/src/commands/config/reset.py
mio_decomp/src/commands/config/set.py
mio_decomp/src/commands/decompile/__init__.py
mio_decomp/src/commands/decompile/decompile_multi.py
mio_decomp/src/commands/decompile/decompile_single.py
mio_decomp/src/commands/version.py
mio_decomp/src/config.py
mio_decomp/src/libraries/__init__.py
mio_decomp/src/libraries/decompiler/__init__.py
mio_decomp/src/libraries/decompiler/constants.py
mio_decomp/src/libraries/decompiler/decompiler.py
mio_decomp-0.0.1.dist-info/WHEEL
mio_decomp-0.0.1.dist-info/entry_points.txt
mio_decomp-0.0.1.dist-info/METADATA
mio_decomp-0.0.1.dist-info/RECORD
