Metadata-Version: 2.3
Name: mio_decomp
Version: 0.0.1
Summary: A CLI for decompiling the .gin files from MIO: Memories in Orbit.
Keywords: decompile,decompiler,mio,memories-in-orbit
Author: ShackledMars261
License: MIT
Requires-Dist: lz4>=4.4.5
Requires-Dist: pydantic>=2.12.5
Requires-Dist: rich>=14.3.1
Requires-Dist: typer>=0.21.1
Requires-Dist: zstandard>=0.25.0
Requires-Python: >=3.13
Project-URL: Bug Tracker, https://github.com/ShackledMars261/mio-decomp-cli/issues
Project-URL: Homepage, https://github.com/ShackledMars261/mio-decomp-cli
